AUTHORS
CHANGELOG
LICENSE
MANIFEST.in
README.rst
setup.py
bronto/__init__.py
bronto/client.py
bronto_python.egg-info/PKG-INFO
bronto_python.egg-info/SOURCES.txt
bronto_python.egg-info/dependency_links.txt
bronto_python.egg-info/requires.txt
bronto_python.egg-info/top_level.txt