Metadata-Version: 1.1
Name: bronto-python
Version: 0.8.0
Summary: A python wrapper around Bronto's SOAP API
Home-page: http://github.com/Scotts-Marketplace/bronto-python/
Author: Joey Wilhelm
Author-email: joey@scottsmarketplace.com
License: Apache
Download-URL: http://github.com/Scotts-Marketplace/bronto-python/archive/0.8.0.tar.gz
Keywords: bronto,soap,marketing
Platform: UNKNOWN
Classifier: Development Status :: 4 - Beta
Classifier: Environment :: Web Environment
Classifier: Intended Audience :: Developers
Classifier: License :: OSI Approved :: Apache Software License
Classifier: Natural Language :: English
Classifier: Operating System :: OS Independent
Classifier: Programming Language :: Python
Classifier: Programming Language :: Python :: 2.7
Classifier: Programming Language :: Python :: 3
Classifier: Programming Language :: Python :: 3.2
Classifier: Programming Language :: Python :: 3.3
Classifier: Programming Language :: Python :: 3.4
